{
  "kind": "singleType",
  "collectionName": "tech_labs",
  "info": {
    "singularName": "tech-lab",
    "pluralName": "tech-labs",
    "displayName": "TechLab"
  },
  "options": {
    "draftAndPublish": true
  },
  "pluginOptions": {
    "i18n": {
      "localized": true
    }
  },
  "attributes": {
    "Sections": {
      "type": "dynamiczone",
      "pluginOptions": {
        "i18n": {
          "localized": true
        }
      },
      "components": [
        "hero-section.hero-tech-lab",
        "content-section.content-tech-lab"
      ]
    }
  }
}
